LICENSE
MANIFEST.in
README.rst
config.example.cfg
pytest.ini
setup.cfg
setup.py
labelord/__init__.py
labelord/__main__.py
labelord/cli.py
labelord/consts.py
labelord/github.py
labelord/helpers.py
labelord/printing.py
labelord/run_logic.py
labelord/web.py
labelord.egg-info/PKG-INFO
labelord.egg-info/SOURCES.txt
labelord.egg-info/dependency_links.txt
labelord.egg-info/entry_points.txt
labelord.egg-info/not-zip-safe
labelord.egg-info/requires.txt
labelord.egg-info/top_level.txt
labelord/static/bootstrap.min.css
labelord/static/style.css
labelord/templates/error.html
labelord/templates/header.html
labelord/templates/index.html
labelord/templates/layout.html
tests/conftest.py
tests/__pycache__/conftest.cpython-36-PYTEST.pyc
tests/fixtures/utils.py
tests/fixtures/cassettes/test_bad_config.test_no_labels.json
tests/fixtures/cassettes/test_bad_config.test_no_repos.json
tests/fixtures/cassettes/test_bad_config.test_no_token.json
tests/fixtures/cassettes/test_bad_config.test_no_webhook_secret.json
tests/fixtures/cassettes/test_basic.test_activate_webhook.json
tests/fixtures/cassettes/test_basic.test_homepage.json
tests/fixtures/cassettes/test_basic.test_labels.json
tests/fixtures/cassettes/test_basic.test_reload.json
tests/fixtures/cassettes/test_basic.test_repos.json
tests/fixtures/cassettes/test_basic.test_webhook_ping.json
tests/fixtures/cassettes/test_github.test_create_label_for_existing_repo.json
tests/fixtures/cassettes/test_github.test_create_label_for_unexisting_repo.json
tests/fixtures/cassettes/test_github.test_create_label_that_already_exists.json
tests/fixtures/cassettes/test_github.test_create_label_with_bad_token.json
tests/fixtures/cassettes/test_github.test_create_label_with_weird_color.json
tests/fixtures/cassettes/test_github.test_delete_label_for_existing_repo.json
tests/fixtures/cassettes/test_github.test_delete_label_for_unexisting_repo.json
tests/fixtures/cassettes/test_github.test_delete_label_that_doesnt_exist.json
tests/fixtures/cassettes/test_github.test_error_properties.json
tests/fixtures/cassettes/test_github.test_list_labels_from_existing_repo.json
tests/fixtures/cassettes/test_github.test_list_labels_from_unexisting_repo.json
